README.md
cleanroom_schema/_version.py
cleanroom_schema/datamodel/__init__.py
cleanroom_schema/datamodel/cleanroom_schema.py
cleanroom_schema/schema/cleanroom_schema.yaml
cleanroom_schema/test_publishability.py
cleanroom_schema-0.1.3.dist-info/entry_points.txt
cleanroom_schema-0.1.3.dist-info/METADATA
cleanroom_schema-0.1.3.dist-info/WHEEL
cleanroom_schema-0.1.3.dist-info/LICENSE
cleanroom_schema-0.1.3.dist-info/RECORD
