Metadata-Version: 2.1
Name: cleanroom-schema
Version: 0.1.3
Summary: Cleanroom reboot of NMDC schema
License: MIT
Author: Mark Andrew Miller
Author-email: MAM@lbl.gov
Requires-Python: >=3.9,<4.0
Classifier: License :: OSI Approved :: MIT License
Classifier: Programming Language :: Python :: 3
Classifier: Programming Language :: Python :: 3.9
Classifier: Programming Language :: Python :: 3.10
Classifier: Programming Language :: Python :: 3.11
Provides-Extra: docs
Requires-Dist: cruft (>=2.11.1,<3.0.0)
Requires-Dist: deepdiff[cli] (>=6.2.2,<7.0.0)
Requires-Dist: linkml-runtime (>=1.1.24,<2.0.0)
Requires-Dist: schema-automator (>=0.2.10,<0.3.0)
